setup.py
goenv/__init__.py
goenv/goenv
goenv/goenv.sh
goenv/gopath.py
goenv.egg-info/PKG-INFO
goenv.egg-info/SOURCES.txt
goenv.egg-info/dependency_links.txt
goenv.egg-info/entry_points.txt
goenv.egg-info/pbr.json
goenv.egg-info/top_level.txt
goenv/data/goimport.go
goenv/data/Godeps/Godeps.json
goenv/data/Godeps/Readme
goenv/data/Godeps/_workspace/.gitignore
goenv/data/Godeps/_workspace/src/github.com/constabulary/gb/.gitignore
goenv/data/Godeps/_workspace/src/github.com/constabulary/gb/LICENSE
goenv/data/Godeps/_workspace/src/github.com/constabulary/gb/README.md
goenv/data/Godeps/_workspace/src/github.com/constabulary/gb/build.go
goenv/data/Godeps/_workspace/src/github.com/constabulary/gb/build_test.go
goenv/data/Godeps/_workspace/src/github.com/constabulary/gb/cgo.go
goenv/data/Godeps/_workspace/src/github.com/constabulary/gb/cgo14.go
goenv/data/Godeps/_workspace/src/github.com/constabulary/gb/cgo15.go
goenv/data/Godeps/_workspace/src/github.com/constabulary/gb/context.go
goenv/data/Godeps/_workspace/src/github.com/constabulary/gb/context_test.go
goenv/data/Godeps/_workspace/src/github.com/constabulary/gb/defaultcc.go
goenv/data/Godeps/_workspace/src/github.com/constabulary/gb/defaultcc_bsd.go
goenv/data/Godeps/_workspace/src/github.com/constabulary/gb/gb.go
goenv/data/Godeps/_workspace/src/github.com/constabulary/gb/gb_test.go
goenv/data/Godeps/_workspace/src/github.com/constabulary/gb/gc.go
goenv/data/Godeps/_workspace/src/github.com/constabulary/gb/gc14.go
goenv/data/Godeps/_workspace/src/github.com/constabulary/gb/gc15.go
goenv/data/Godeps/_workspace/src/github.com/constabulary/gb/install.go
goenv/data/Godeps/_workspace/src/github.com/constabulary/gb/log.go
goenv/data/Godeps/_workspace/src/github.com/constabulary/gb/package.go
goenv/data/Godeps/_workspace/src/github.com/constabulary/gb/package_test.go
goenv/data/Godeps/_workspace/src/github.com/constabulary/gb/project.go
goenv/data/Godeps/_workspace/src/github.com/constabulary/gb/stdlib.go
goenv/data/Godeps/_workspace/src/github.com/constabulary/gb/target.go
goenv/data/Godeps/_workspace/src/github.com/constabulary/gb/wercker.yml
