Metadata-Version: 1.0
Name: goenv
Version: 0.0.14
Summary: Golang environment manager
Home-page: https://github.com/biinilya/goenv
Author: Ilya Biin
Author-email: me@ilyabiin.com
License: UNKNOWN
Platform: UNKNOWN
